django_simple_elasticsearch-2.2.1.dist-info/DESCRIPTION.rst
django_simple_elasticsearch-2.2.1.dist-info/METADATA
django_simple_elasticsearch-2.2.1.dist-info/RECORD
django_simple_elasticsearch-2.2.1.dist-info/WHEEL
django_simple_elasticsearch-2.2.1.dist-info/metadata.json
django_simple_elasticsearch-2.2.1.dist-info/top_level.txt
simple_elasticsearch/__init__.py
simple_elasticsearch/exceptions.py
simple_elasticsearch/mixins.py
simple_elasticsearch/models.py
simple_elasticsearch/search.py
simple_elasticsearch/settings.py
simple_elasticsearch/signals.py
simple_elasticsearch/tests.py
simple_elasticsearch/utils.py
simple_elasticsearch/management/__init__.py
simple_elasticsearch/management/commands/__init__.py
simple_elasticsearch/management/commands/es_manage.py
