Metadata-Version: 2.0
Name: django-simple-elasticsearch
Version: 2.2.1
Summary: Simple ElasticSearch indexing integration for Django.
Home-page: https://github.com/jaddison/django-simple-elasticsearch
Author: James Addison
Author-email: addi00+github.com@gmail.com
License: BSD
Keywords: django simple elasticsearch search indexing
Platform: UNKNOWN
Classifier: Development Status :: 4 - Beta
Classifier: License :: OSI Approved :: BSD License
Classifier: Intended Audience :: Developers
Classifier: Environment :: Web Environment
Classifier: Programming Language :: Python
Classifier: Framework :: Django
Classifier: Topic :: Internet :: WWW/HTTP :: WSGI
Classifier: Natural Language :: English
Classifier: Programming Language :: Python :: 2
Classifier: Programming Language :: Python :: 2.7
Classifier: Programming Language :: Python :: 3
Classifier: Programming Language :: Python :: 3.3
Classifier: Programming Language :: Python :: 3.4
Classifier: Programming Language :: Python :: 3.5
Classifier: Programming Language :: Python :: 3.6
Requires-Dist: elasticsearch (>=2.0.0)
